sorbetto/__init__.py
sorbetto/annotation/__init__.py
sorbetto/annotation/abstract_annotation.py
sorbetto/annotation/annotation_curve_fixed_class_priors.py
sorbetto/annotation/annotation_curve_fixed_prediction_rates.py
sorbetto/annotation/annotation_frontiers_between_rankings.py
sorbetto/annotation/annotation_geometric.py
sorbetto/annotation/annotation_isovalue_curves.py
sorbetto/annotation/annotation_text.py
sorbetto/core/__init__.py
sorbetto/core/entity.py
sorbetto/core/importance.py
sorbetto/core/performance_ordering_induced_by_one_score.py
sorbetto/core/relations.py
sorbetto/core/types.py
sorbetto/flavor/__init__.py
sorbetto/flavor/abstract_flavor.py
sorbetto/flavor/abstract_numeric_flavor.py
sorbetto/flavor/abstract_symbolic_flavor.py
sorbetto/flavor/best_flavor.py
sorbetto/flavor/correlation_flavor.py
sorbetto/flavor/entity_flavor.py
sorbetto/flavor/ranking_flavor.py
sorbetto/flavor/value_flavor.py
sorbetto/flavor/worst_flavor.py
sorbetto/geometry/__init__.py
sorbetto/geometry/abstract_geometric_object_2d.py
sorbetto/geometry/bilinear_curve.py
sorbetto/geometry/conic.py
sorbetto/geometry/line.py
sorbetto/geometry/line_segment.py
sorbetto/geometry/linear_fractional_transformation.py
sorbetto/geometry/pencil_of_lines.py
sorbetto/geometry/point.py
sorbetto/parameterization/__init__.py
sorbetto/parameterization/abstract_parameterization.py
sorbetto/parameterization/parameterization_default.py
sorbetto/performance/__init__.py
sorbetto/performance/abstract_performance.py
sorbetto/performance/abstract_score.py
sorbetto/performance/constraint_fixed_class_priors.py
sorbetto/performance/constraint_fixed_prediction_rates.py
sorbetto/performance/finite_set_of_two_class_classification_performances.py
sorbetto/performance/roc.py
sorbetto/performance/two_class_classification_performance.py
sorbetto/performance/distribution/__init__.py
sorbetto/performance/distribution/abstract_distribution_of_two_class_classification_performances.py
sorbetto-0.1.0.dist-info/licenses/LICENSE
sorbetto-0.1.0.dist-info/METADATA
sorbetto-0.1.0.dist-info/WHEEL
sorbetto-0.1.0.dist-info/top_level.txt
sorbetto-0.1.0.dist-info/RECORD
