Metadata-Version: 2.4
Name: Sorbetto
Version: 0.1.0
Summary: A Python Library for Producing Classification Tiles With Different Flavors
Author-email: "Sébastien Piérard et al." <Sebastien.Pierard@gmail.com>, Sébastien Piérard <Sebastien.Pierard@gmail.com>, Anaïs Halin <anais.halin@gmail.com>, François Marelli <francois.marelli@umons.ac.be>, Simon Pernas <simonpernas@orange.fr>, Jérôme Pierre <jepi1202@gmail.com>
License-Expression: Apache-2.0
Project-URL: Documentation, https://sorbetto.readthedocs.io/en/latest/
Project-URL: Source, https://github.com/uliege-performance/sorbetto
Project-URL: Issues, https://github.com/uliege-performance/sorbetto/issues
Classifier: Development Status :: 3 - Alpha
Classifier: Intended Audience :: Science/Research
Classifier: Topic :: Scientific/Engineering
Classifier: Programming Language :: Python :: 3
Classifier: Programming Language :: Python :: 3.12
Classifier: Operating System :: Microsoft :: Windows
Classifier: Operating System :: POSIX
Classifier: Operating System :: Unix
Classifier: Operating System :: MacOS
Requires-Python: >=3.12
License-File: LICENSE
Requires-Dist: numpy>=1.20.0
Requires-Dist: matplotlib>=3.6.0
Requires-Dist: scipy>=1.16.0
Requires-Dist: jax
Requires-Dist: tqdm
Provides-Extra: dev
Requires-Dist: ruff>=0.12; extra == "dev"
Requires-Dist: pre-commit>=4.3; extra == "dev"
Requires-Dist: pytest>=8; extra == "dev"
Provides-Extra: dist
Requires-Dist: build; extra == "dist"
Requires-Dist: twine; extra == "dist"
Provides-Extra: doc
Requires-Dist: sphinx; extra == "doc"
Requires-Dist: sphinx-rtd-theme; extra == "doc"
Requires-Dist: sphinxcontrib-bibtex; extra == "doc"
Requires-Dist: nbsphinx; extra == "doc"
Requires-Dist: sphinx-gallery; extra == "doc"
Requires-Dist: sphinxcontrib-apidoc; extra == "doc"
Dynamic: license-file
